logcaster/__init__.py
logcaster/discord.py
logcaster/discord_utils/__init__.py
logcaster/discord_utils/abstraction.py
logcaster/discord_utils/discord_client.py
logcaster/discord_utils/discord_embed.py
logcaster/discord_utils/models.py
logcaster/exceptions.py
logcaster/formatters.py
logcaster/handlers.py
logcaster/settings/__init__.py
logcaster/settings/_environment.py
logcaster/settings/_models.py
logcaster/telegram.py
logcaster/utils.py
logcaster-0.5.1.dist-info/LICENSE
logcaster-0.5.1.dist-info/METADATA
logcaster-0.5.1.dist-info/WHEEL
logcaster-0.5.1.dist-info/RECORD
