Metadata-Version: 2.3
Name: logcaster
Version: 0.5.1
Summary: Logging handlers to send logs to discord and telegram
License: MIT
Keywords: logging
Author: LeandroDeJesus-S
Author-email: jstleandro@gmail.com
Requires-Python: >=3.10,<4.0
Classifier: Development Status :: 2 - Pre-Alpha
Classifier: Intended Audience :: Developers
Classifier: License :: OSI Approved :: MIT License
Classifier: Natural Language :: English
Classifier: Operating System :: OS Independent
Classifier: Programming Language :: Python
Classifier: Programming Language :: Python :: 3
Classifier: Framework :: Django CMS :: 3.10
Classifier: Topic :: Software Development :: Debuggers
Classifier: Topic :: System :: Logging
Classifier: Topic :: Utilities
Requires-Dist: httpx (>=0.28.1,<0.29.0)
Requires-Dist: pydantic (>=2.11.7,<3.0.0)
Requires-Dist: pydantic-settings (>=2.8.1,<3.0.0)
Requires-Dist: tabulate (>=0.9.0,<0.10.0)
Project-URL: Repository, https://github.com/LeandroDeJesus-S/logcaster
Project-URL: issues, https://github.com/LeandroDeJesus-S/logcaster/issues
